{
  "width": 14,
  "height": 14,
  "elements": [
    {
      "type": "Polyline",
      "background": "#D8D8D8",
      "borderColor": "#979797",
      "fillRule": "evenodd",
      "gradientPack": [
        "linear",
        1,
        0.5,
        0,
        0.5,
        0,
        "rgba(255,255,255,0.2)",
        1,
        "rgb(255,255,255)"
      ],
      "pixelPerfect": true,
      "opacity": 0.4,
      "points": [
        {
          "x": 12.60719,
          "y": 10.2373
        },
        {
          "x": 12.60719,
          "y": 3.76267
        },
        {
          "x": 7,
          "y": 0.52538
        },
        {
          "x": 7,
          "y": 6.99998
        },
        {
          "x": 12.60719,
          "y": 10.2373
        }
      ],
      "segments": [
        1,
        2,
        2,
        2,
        2,
        5
      ]
    },
    {
      "type": "Polyline",
      "background": "#D8D8D8",
      "borderColor": "#979797",
      "fillRule": "evenodd",
      "gradientPack": [
        "linear",
        1,
        0.5,
        0,
        0.5,
        0,
        "rgba(255,255,255,0.2)",
        1,
        "rgb(255,255,255)"
      ],
      "pixelPerfect": true,
      "opacity": 0.2,
      "scaleX": -1,
      "points": [
        {
          "x": 7,
          "y": 10.2373
        },
        {
          "x": 7,
          "y": 3.76267
        },
        {
          "x": 1.39281,
          "y": 0.52538
        },
        {
          "x": 1.39281,
          "y": 6.99998
        },
        {
          "x": 7,
          "y": 10.2373
        }
      ],
      "segments": [
        1,
        2,
        2,
        2,
        2,
        5
      ]
    },
    {
      "type": "Polyline",
      "background": "#D8D8D8",
      "borderColor": "#979797",
      "fillRule": "evenodd",
      "gradientPack": [
        "linear",
        1,
        0.5,
        0,
        0.5,
        0,
        "rgb(255,255,255)",
        1,
        "rgba(255,255,255,0.2)"
      ],
      "pixelPerfect": true,
      "opacity": 0.8,
      "points": [
        {
          "x": 7,
          "y": 13.47462
        },
        {
          "x": 7,
          "y": 6.99999
        },
        {
          "x": 1.39281,
          "y": 3.7627
        },
        {
          "x": 1.39281,
          "y": 10.2373
        },
        {
          "x": 7,
          "y": 13.47462
        }
      ],
      "segments": [
        1,
        2,
        2,
        2,
        2,
        5
      ]
    },
    {
      "type": "Polyline",
      "background": "#D8D8D8",
      "borderColor": "#979797",
      "fillRule": "evenodd",
      "gradientPack": [
        "linear",
        0,
        0.5,
        1,
        0.5,
        0,
        "rgb(255,255,255)",
        1,
        "rgba(255,255,255,0.2)"
      ],
      "pixelPerfect": true,
      "opacity": 0.6,
      "points": [
        {
          "x": 7,
          "y": 13.47462
        },
        {
          "x": 7,
          "y": 6.99999
        },
        {
          "x": 12.60719,
          "y": 3.7627
        },
        {
          "x": 12.60719,
          "y": 10.2373
        },
        {
          "x": 7,
          "y": 13.47462
        }
      ],
      "segments": [
        1,
        2,
        2,
        2,
        2,
        5
      ]
    },
    {
      "type": "Polyline",
      "background": "#D8D8D8",
      "borderColor": "#979797",
      "fillRule": "evenodd",
      "gradientPack": [
        "linear",
        0.5,
        0,
        0.5,
        1,
        0,
        "rgba(255,255,255,0.2)",
        1,
        "rgb(255,255,255)"
      ],
      "pixelPerfect": true,
      "opacity": 0.4,
      "points": [
        {
          "x": 1.39281,
          "y": 3.7627
        },
        {
          "x": 0.06794,
          "y": 5.04653
        },
        {
          "x": 5.67513,
          "y": 1.80924
        },
        {
          "x": 7,
          "y": 0.52538
        },
        {
          "x": 1.39281,
          "y": 3.7627
        },
        {
          "x": 1.39281,
          "y": 3.7627
        }
      ]
    },
    {
      "type": "Polyline",
      "background": "#D8D8D8",
      "borderColor": "#979797",
      "fillRule": "evenodd",
      "gradientPack": [
        "linear",
        0.5,
        0,
        0.5,
        1,
        0,
        "rgba(255,255,255,0.2)",
        1,
        "rgb(255,255,255)"
      ],
      "pixelPerfect": true,
      "opacity": 0.2,
      "scaleX": -1,
      "points": [
        {
          "x": 8.32487,
          "y": 3.7627
        },
        {
          "x": 7,
          "y": 5.04653
        },
        {
          "x": 12.60719,
          "y": 1.80924
        },
        {
          "x": 13.93206,
          "y": 0.52538
        },
        {
          "x": 8.32487,
          "y": 3.7627
        },
        {
          "x": 8.32487,
          "y": 3.7627
        }
      ]
    },
    {
      "type": "Polyline",
      "background": "#D8D8D8",
      "borderColor": "#979797",
      "fillRule": "evenodd",
      "gradientPack": [
        "linear",
        0.5,
        0,
        0.5,
        1,
        0,
        "rgba(255,255,255,0.2)",
        1,
        "rgb(255,255,255)"
      ],
      "pixelPerfect": true,
      "scaleX": -1,
      "points": [
        {
          "x": 1.39281,
          "y": 10.00245
        },
        {
          "x": 0.06794,
          "y": 6.99999
        },
        {
          "x": 5.67513,
          "y": 3.7627
        },
        {
          "x": 7,
          "y": 6.76513
        },
        {
          "x": 1.39281,
          "y": 10.00245
        },
        {
          "x": 1.39281,
          "y": 10.00245
        }
      ]
    },
    {
      "type": "Polyline",
      "background": "#D8D8D8",
      "borderColor": "#979797",
      "fillRule": "evenodd",
      "gradientPack": [
        "linear",
        0.5,
        0,
        0.5,
        1,
        0,
        "rgba(255,255,255,0.2)",
        1,
        "rgb(255,255,255)"
      ],
      "pixelPerfect": true,
      "opacity": 0.6,
      "points": [
        {
          "x": 8.32487,
          "y": 10.00245
        },
        {
          "x": 7,
          "y": 6.99999
        },
        {
          "x": 12.60719,
          "y": 3.7627
        },
        {
          "x": 13.93206,
          "y": 6.76513
        },
        {
          "x": 8.32487,
          "y": 10.00245
        },
        {
          "x": 8.32487,
          "y": 10.00245
        }
      ]
    }
  ]
}